numbast/__init__.py
numbast/__main__.py
numbast/class_template.py
numbast/enum.py
numbast/errors.py
numbast/function.py
numbast/functor.py
numbast/shim_writer.py
numbast/struct.py
numbast/types.py
numbast/utils.py
numbast/static/__init__.py
numbast/static/enum.py
numbast/static/function.py
numbast/static/renderer.py
numbast/static/struct.py
numbast/static/typedef.py
numbast/static/types.py
numbast/static/tests/conftest.py
numbast/static/tests/test_bf16_support.py
numbast/static/tests/test_conflict_shim_names.py
numbast/static/tests/test_enum_static_bindings.py
numbast/static/tests/test_function_static_bindings.py
numbast/static/tests/test_link_two_files.py
numbast/static/tests/test_multiple_decls.py
numbast/static/tests/test_operator_bindings.py
numbast/static/tests/test_static_demo.py
numbast/static/tests/test_struct_static_bindings.py
numbast/tools/__init__.py
numbast/tools/static_binding_generator.py
numbast/tools/yaml_tags.py
numbast/tools/tests/conftest.py
numbast/tools/tests/test_additional_includes.py
numbast/tools/tests/test_bypass_parsing_error.py
numbast/tools/tests/test_cc.py
numbast/tools/tests/test_cli.py
numbast/tools/tests/test_macros.py
numbast/tools/tests/test_module_callbacks.py
numbast/tools/tests/test_output_name.py
numbast/tools/tests/test_predefined_macros.py
numbast/tools/tests/test_prefix_removal.py
numbast/tools/tests/test_repro_info.py
numbast/tools/tests/test_shim_include_override.py
numbast/tools/tests/test_skip_prefix.py
numbast/tools/tests/test_symbol_exposure.py
numbast/tools/tests/test_use_cooperative.py
numbast/tools/tests/test_use_separate_registry.py
numbast-0.6.0.dist-info/METADATA
numbast-0.6.0.dist-info/WHEEL
numbast-0.6.0.dist-info/entry_points.txt
numbast-0.6.0.dist-info/top_level.txt
numbast-0.6.0.dist-info/RECORD
